[
  {
    "id": 6419046177,
    "username": null,
    "first_name": "Nk",
    "last_name": null,
    "premium": false,
    "phone": null,
    "last_seen": null,
    "comment_count": 1,
    "last_comment_date": "2025-02-05T18:19:34+00:00"
  },
  {
    "id": 7133291173,
    "username": null,
    "first_name": "Наталия",
    "last_name": "Будзинская",
    "premium": false,
    "phone": null,
    "last_seen": null,
    "comment_count": 1,
    "last_comment_date": "2025-02-05T18:02:59+00:00"
  },
  {
    "id": 5272153908,
    "username": null,
    "first_name": "Лариса",
    "last_name": "Шумакова",
    "premium": false,
    "phone": null,
    "last_seen": null,
    "comment_count": 3,
    "last_comment_date": "2025-02-05T17:45:50+00:00"
  },
  {
    "id": 1295596463,
    "username": "okhgtu",
    "first_name": "Artem",
    "last_name": "Cobain",
    "premium": false,
    "phone": null,
    "last_seen": null,
    "comment_count": 6,
    "last_comment_date": "2025-02-05T17:43:35+00:00"
  },
  {
    "id": 5185922071,
    "username": null,
    "first_name": "Μισάνθρωπος",
    "last_name": null,
    "premium": false,
    "phone": null,
    "last_seen": null,
    "comment_count": 2,
    "last_comment_date": "2025-02-05T17:38:47+00:00"
  },
  {
    "id": 240939202,
    "username": "lex0n",
    "first_name": "Olexii",
    "last_name": null,
    "premium": false,
    "phone": null,
    "last_seen": null,
    "comment_count": 1,
    "last_comment_date": "2025-02-05T17:32:18+00:00"
  },
  {
    "id": 1690611782,
    "username": null,
    "first_name": "Sergii",
    "last_name": null,
    "premium": false,
    "phone": null,
    "last_seen": null,
    "comment_count": 1,
    "last_comment_date": "2025-02-05T17:30:00+00:00"
  },
  {
    "id": 488306141,
    "username": "ushakabrah",
    "first_name": "Yaroslav 🦋🌪️🌀",
    "last_name": null,
    "premium": false,
    "phone": null,
    "last_seen": null,
    "comment_count": 1,
    "last_comment_date": "2025-02-05T17:11:39+00:00"
  },
  {
    "id": 448962034,
    "username": "mivoiceua",
    "first_name": "Max",
    "last_name": null,
    "premium": false,
    "phone": null,
    "last_seen": null,
    "comment_count": 1,
    "last_comment_date": "2025-02-05T17:10:24+00:00"
  },
  {
    "id": 5274081845,
    "username": "ukrainka58",
    "first_name": "Олена",
    "last_name": "Юрьєва",
    "premium": false,
    "phone": null,
    "last_seen": null,
    "comment_count": 1,
    "last_comment_date": "2025-02-05T17:05:22+00:00"
  },
  {
    "id": 1327054333,
    "username": null,
    "first_name": ".",
    "last_name": "Pavel",
    "premium": false,
    "phone": null,
    "last_seen": null,
    "comment_count": 1,
    "last_comment_date": "2025-02-05T17:00:18+00:00"
  },
  {
    "id": 5896339979,
    "username": null,
    "first_name": "Олег",
    "last_name": "Проскуров",
    "premium": false,
    "phone": null,
    "last_seen": null,
    "comment_count": 1,
    "last_comment_date": "2025-02-05T16:53:46+00:00"
  },
  {
    "id": 529475241,
    "username": "alexander_chaikovsky",
    "first_name": "Alexander",
    "last_name": "Ch",
    "premium": true,
    "phone": null,
    "last_seen": null,
    "comment_count": 1,
    "last_comment_date": "2025-02-05T16:47:52+00:00"
  },
  {
    "id": 7859521970,
    "username": null,
    "first_name": "Марго",
    "last_name": null,
    "premium": false,
    "phone": null,
    "last_seen": null,
    "comment_count": 1,
    "last_comment_date": "2025-02-05T16:39:39+00:00"
  },
  {
    "id": 581485918,
    "username": null,
    "first_name": "A",
    "last_name": null,
    "premium": false,
    "phone": null,
    "last_seen": null,
    "comment_count": 1,
    "last_comment_date": "2025-02-05T16:34:02+00:00"
  },
  {
    "id": 5100257031,
    "username": null,
    "first_name": "Alex",
    "last_name": null,
    "premium": false,
    "phone": null,
    "last_seen": null,
    "comment_count": 1,
    "last_comment_date": "2025-02-05T16:25:39+00:00"
  },
  {
    "id": 562527833,
    "username": "vovi44",
    "first_name": "Владимир",
    "last_name": null,
    "premium": false,
    "phone": null,
    "last_seen": null,
    "comment_count": 3,
    "last_comment_date": "2025-02-05T16:16:02+00:00"
  },
  {
    "id": 884571729,
    "username": "djhidj",
    "first_name": "Jason",
    "last_name": null,
    "premium": false,
    "phone": null,
    "last_seen": null,
    "comment_count": 1,
    "last_comment_date": "2025-02-05T16:15:17+00:00"
  },
  {
    "id": 302343372,
    "username": null,
    "first_name": "Marrakesh",
    "last_name": null,
    "premium": false,
    "phone": null,
    "last_seen": null,
    "comment_count": 1,
    "last_comment_date": "2025-02-05T16:11:05+00:00"
  },
  {
    "id": 127910544,
    "username": null,
    "first_name": "Zolotykh Natalia",
    "last_name": null,
    "premium": false,
    "phone": null,
    "last_seen": null,
    "comment_count": 1,
    "last_comment_date": "2025-02-05T16:04:25+00:00"
  },
  {
    "id": 499179401,
    "username": "error_name_501",
    "first_name": "error_name_501",
    "last_name": null,
    "premium": false,
    "phone": null,
    "last_seen": null,
    "comment_count": 1,
    "last_comment_date": "2025-02-05T16:04:02+00:00"
  },
  {
    "id": 6523987773,
    "username": null,
    "first_name": "NORTON",
    "last_name": null,
    "premium": false,
    "phone": null,
    "last_seen": null,
    "comment_count": 1,
    "last_comment_date": "2025-02-05T16:03:47+00:00"
  },
  {
    "id": 2052780744,
    "username": null,
    "first_name": "Rybachok Gennadii",
    "last_name": null,
    "premium": false,
    "phone": null,
    "last_seen": null,
    "comment_count": 1,
    "last_comment_date": "2025-02-05T16:02:30+00:00"
  },
  {
    "id": 7573457764,
    "username": null,
    "first_name": "Qwerty",
    "last_name": null,
    "premium": false,
    "phone": null,
    "last_seen": null,
    "comment_count": 1,
    "last_comment_date": "2025-02-05T16:01:52+00:00"
  },
  {
    "id": 6686420064,
    "username": "Natalya_yeva",
    "first_name": "Наталья",
    "last_name": null,
    "premium": false,
    "phone": null,
    "last_seen": null,
    "comment_count": 1,
    "last_comment_date": "2025-02-05T15:53:14+00:00"
  },
  {
    "id": 1545898454,
    "username": null,
    "first_name": "Zаlina",
    "last_name": null,
    "premium": false,
    "phone": null,
    "last_seen": null,
    "comment_count": 1,
    "last_comment_date": "2025-02-05T15:45:44+00:00"
  },
  {
    "id": 5197702348,
    "username": "SenorNicandro",
    "first_name": "SeñorNicandro",
    "last_name": null,
    "premium": true,
    "phone": null,
    "last_seen": null,
    "comment_count": 2,
    "last_comment_date": "2025-02-05T15:45:03+00:00"
  },
  {
    "id": 400809138,
    "username": null,
    "first_name": "Kalina",
    "last_name": "404",
    "premium": false,
    "phone": null,
    "last_seen": null,
    "comment_count": 2,
    "last_comment_date": "2025-02-05T15:44:59+00:00"
  },
  {
    "id": 1631418597,
    "username": null,
    "first_name": "Тетяна",
    "last_name": "Познахор /Позняк/",
    "premium": false,
    "phone": null,
    "last_seen": null,
    "comment_count": 1,
    "last_comment_date": "2025-02-05T15:43:30+00:00"
  },
  {
    "id": 7086009962,
    "username": null,
    "first_name": "Olga",
    "last_name": null,
    "premium": false,
    "phone": null,
    "last_seen": null,
    "comment_count": 1,
    "last_comment_date": "2025-02-05T15:42:04+00:00"
  },
  {
    "id": 6281468270,
    "username": null,
    "first_name": "Дамир",
    "last_name": "Фаизов.",
    "premium": false,
    "phone": null,
    "last_seen": null,
    "comment_count": 1,
    "last_comment_date": "2025-02-05T15:39:48+00:00"
  },
  {
    "id": 5088104620,
    "username": "Tashaswiss",
    "first_name": "Natalya",
    "last_name": "H",
    "premium": false,
    "phone": null,
    "last_seen": null,
    "comment_count": 1,
    "last_comment_date": "2025-02-05T15:34:47+00:00"
  },
  {
    "id": 1643506017,
    "username": "Irinalaskevich777",
    "first_name": "Ирина Ласкевич",
    "last_name": null,
    "premium": false,
    "phone": null,
    "last_seen": null,
    "comment_count": 1,
    "last_comment_date": "2025-02-05T15:34:04+00:00"
  },
  {
    "id": 5316591032,
    "username": "nik8752",
    "first_name": "Nikitа",
    "last_name": null,
    "premium": false,
    "phone": null,
    "last_seen": null,
    "comment_count": 1,
    "last_comment_date": "2025-02-05T15:34:00+00:00"
  },
  {
    "id": 363536379,
    "username": null,
    "first_name": "Натали",
    "last_name": null,
    "premium": false,
    "phone": null,
    "last_seen": null,
    "comment_count": 1,
    "last_comment_date": "2025-02-05T15:33:59+00:00"
  },
  {
    "id": 5800102757,
    "username": null,
    "first_name": "Гортаур",
    "last_name": "Жорстокий",
    "premium": false,
    "phone": null,
    "last_seen": null,
    "comment_count": 1,
    "last_comment_date": "2025-02-05T15:32:10+00:00"
  },
  {
    "id": 6600241072,
    "username": "Boris_97",
    "first_name": "Борис",
    "last_name": null,
    "premium": false,
    "phone": null,
    "last_seen": null,
    "comment_count": 4,
    "last_comment_date": "2025-02-05T15:30:05+00:00"
  },
  {
    "id": 6315009783,
    "username": "B78Terra",
    "first_name": "Terras",
    "last_name": null,
    "premium": false,
    "phone": null,
    "last_seen": null,
    "comment_count": 6,
    "last_comment_date": "2025-02-05T18:04:29+00:00"
  },
  {
    "id": 562473066,
    "username": "retr0ra1n",
    "first_name": "🐻 гоша медведь 🥰",
    "last_name": null,
    "premium": false,
    "phone": null,
    "last_seen": null,
    "comment_count": 1,
    "last_comment_date": "2025-02-05T15:25:33+00:00"
  },
  {
    "id": 1220910742,
    "username": null,
    "first_name": "Alla",
    "last_name": "Migol",
    "premium": false,
    "phone": null,
    "last_seen": null,
    "comment_count": 1,
    "last_comment_date": "2025-02-05T15:25:05+00:00"
  },
  {
    "id": 1534188925,
    "username": "Underlinch",
    "first_name": "Mike",
    "last_name": null,
    "premium": false,
    "phone": null,
    "last_seen": null,
    "comment_count": 2,
    "last_comment_date": "2025-02-05T15:24:37+00:00"
  },
  {
    "id": 292640338,
    "username": null,
    "first_name": "Alexander",
    "last_name": null,
    "premium": false,
    "phone": null,
    "last_seen": null,
    "comment_count": 1,
    "last_comment_date": "2025-02-05T15:21:49+00:00"
  },
  {
    "id": 8074181972,
    "username": "yehorkka",
    "first_name": "Егор",
    "last_name": null,
    "premium": false,
    "phone": null,
    "last_seen": null,
    "comment_count": 1,
    "last_comment_date": "2025-02-05T15:21:47+00:00"
  },
  {
    "id": 6314105582,
    "username": "Tehnokrat_228",
    "first_name": "Té̄̃ẖnǭ̀kr̥̄̀á̤t 228. (Ꝟęri̭ťą̈̂bl̥̀ē Ƞè̄̃øcəɲ )",
    "last_name": null,
    "premium": false,
    "phone": null,
    "last_seen": null,
    "comment_count": 1,
    "last_comment_date": "2025-02-05T15:21:08+00:00"
  },
  {
    "id": 315603778,
    "username": null,
    "first_name": "Makova",
    "last_name": "Oksana",
    "premium": false,
    "phone": null,
    "last_seen": null,
    "comment_count": 1,
    "last_comment_date": "2025-02-05T18:07:05+00:00"
  },
  {
    "id": 503204011,
    "username": null,
    "first_name": "Andrii",
    "last_name": null,
    "premium": false,
    "phone": null,
    "last_seen": null,
    "comment_count": 2,
    "last_comment_date": "2025-02-05T18:04:39+00:00"
  },
  {
    "id": 5173244145,
    "username": null,
    "first_name": "Наташа",
    "last_name": "Белькова",
    "premium": false,
    "phone": null,
    "last_seen": null,
    "comment_count": 3,
    "last_comment_date": "2025-02-05T17:45:33+00:00"
  },
  {
    "id": 7349402990,
    "username": null,
    "first_name": "Cerebrum",
    "last_name": null,
    "premium": false,
    "phone": null,
    "last_seen": null,
    "comment_count": 4,
    "last_comment_date": "2025-02-05T17:32:28+00:00"
  },
  {
    "id": 1020533497,
    "username": null,
    "first_name": "Vasyl",
    "last_name": "M",
    "premium": false,
    "phone": null,
    "last_seen": null,
    "comment_count": 1,
    "last_comment_date": "2025-02-05T17:14:18+00:00"
  },
  {
    "id": 417410042,
    "username": null,
    "first_name": "Qqq",
    "last_name": null,
    "premium": false,
    "phone": null,
    "last_seen": null,
    "comment_count": 1,
    "last_comment_date": "2025-02-05T17:11:03+00:00"
  },
  {
    "id": 5226171710,
    "username": null,
    "first_name": "Наталья ❤️❤️❤️",
    "last_name": null,
    "premium": false,
    "phone": null,
    "last_seen": null,
    "comment_count": 1,
    "last_comment_date": "2025-02-05T17:10:11+00:00"
  },
  {
    "id": 1439258491,
    "username": "Gnom1239",
    "first_name": "Gnome838",
    "last_name": null,
    "premium": false,
    "phone": null,
    "last_seen": null,
    "comment_count": 2,
    "last_comment_date": "2025-02-05T16:51:50+00:00"
  },
  {
    "id": 5911053566,
    "username": null,
    "first_name": "R",
    "last_name": null,
    "premium": false,
    "phone": null,
    "last_seen": null,
    "comment_count": 10,
    "last_comment_date": "2025-02-05T16:48:53+00:00"
  },
  {
    "id": 7479027148,
    "username": "ne_uletay_ne_uhodi",
    "first_name": "М",
    "last_name": null,
    "premium": false,
    "phone": null,
    "last_seen": null,
    "comment_count": 1,
    "last_comment_date": "2025-02-05T16:41:50+00:00"
  },
  {
    "id": 1180636538,
    "username": null,
    "first_name": "Tanya",
    "last_name": null,
    "premium": false,
    "phone": null,
    "last_seen": null,
    "comment_count": 1,
    "last_comment_date": "2025-02-05T16:27:56+00:00"
  },
  {
    "id": 1147382530,
    "username": null,
    "first_name": "Нафаня",
    "last_name": null,
    "premium": false,
    "phone": null,
    "last_seen": null,
    "comment_count": 1,
    "last_comment_date": "2025-02-05T15:44:04+00:00"
  },
  {
    "id": 6963560700,
    "username": null,
    "first_name": "Bodya",
    "last_name": null,
    "premium": false,
    "phone": null,
    "last_seen": null,
    "comment_count": 1,
    "last_comment_date": "2025-02-05T15:36:43+00:00"
  },
  {
    "id": 230164549,
    "username": "aka182",
    "first_name": "AK",
    "last_name": null,
    "premium": true,
    "phone": null,
    "last_seen": null,
    "comment_count": 1,
    "last_comment_date": "2025-02-05T15:24:17+00:00"
  },
  {
    "id": 5159810460,
    "username": "MaaaarF",
    "first_name": "Vlad",
    "last_name": "Nikolaevich",
    "premium": true,
    "phone": null,
    "last_seen": null,
    "comment_count": 3,
    "last_comment_date": "2025-02-05T15:22:08+00:00"
  },
  {
    "id": 1623282729,
    "username": "mlc_x",
    "first_name": "Civ",
    "last_name": null,
    "premium": false,
    "phone": null,
    "last_seen": null,
    "comment_count": 1,
    "last_comment_date": "2025-02-05T15:21:21+00:00"
  },
  {
    "id": 1190817995,
    "username": null,
    "first_name": "Сергій",
    "last_name": null,
    "premium": false,
    "phone": null,
    "last_seen": null,
    "comment_count": 2,
    "last_comment_date": "2025-02-05T15:10:48+00:00"
  },
  {
    "id": 5326503178,
    "username": null,
    "first_name": "*:*",
    "last_name": null,
    "premium": false,
    "phone": null,
    "last_seen": null,
    "comment_count": 3,
    "last_comment_date": "2025-02-05T15:06:38+00:00"
  },
  {
    "id": 1847558820,
    "username": null,
    "first_name": "шевцова",
    "last_name": "ирина",
    "premium": false,
    "phone": null,
    "last_seen": null,
    "comment_count": 1,
    "last_comment_date": "2025-02-05T15:05:35+00:00"
  },
  {
    "id": 1384521898,
    "username": "joystik",
    "first_name": "543",
    "last_name": null,
    "premium": false,
    "phone": null,
    "last_seen": null,
    "comment_count": 2,
    "last_comment_date": "2025-02-05T14:57:03+00:00"
  },
  {
    "id": 6726120228,
    "username": null,
    "first_name": "До всирачки вільний",
    "last_name": null,
    "premium": false,
    "phone": null,
    "last_seen": null,
    "comment_count": 1,
    "last_comment_date": "2025-02-05T14:55:47+00:00"
  },
  {
    "id": 8166477822,
    "username": null,
    "first_name": "t",
    "last_name": null,
    "premium": true,
    "phone": null,
    "last_seen": null,
    "comment_count": 10,
    "last_comment_date": "2025-02-05T14:55:20+00:00"
  },
  {
    "id": 390586122,
    "username": "nullnull23232",
    "first_name": "///",
    "last_name": null,
    "premium": false,
    "phone": null,
    "last_seen": null,
    "comment_count": 1,
    "last_comment_date": "2025-02-05T14:55:02+00:00"
  },
  {
    "id": 6898561544,
    "username": null,
    "first_name": "iNna💋",
    "last_name": null,
    "premium": false,
    "phone": null,
    "last_seen": null,
    "comment_count": 1,
    "last_comment_date": "2025-02-05T14:53:58+00:00"
  },
  {
    "id": 850602829,
    "username": "Sahok5",
    "first_name": "Saha",
    "last_name": null,
    "premium": false,
    "phone": null,
    "last_seen": null,
    "comment_count": 1,
    "last_comment_date": "2025-02-05T14:51:26+00:00"
  },
  {
    "id": 6242043916,
    "username": null,
    "first_name": "Andrey",
    "last_name": null,
    "premium": false,
    "phone": null,
    "last_seen": null,
    "comment_count": 1,
    "last_comment_date": "2025-02-05T14:51:20+00:00"
  },
  {
    "id": 595848103,
    "username": "Nikita_fan_rammstein",
    "first_name": "Никита",
    "last_name": null,
    "premium": true,
    "phone": null,
    "last_seen": null,
    "comment_count": 6,
    "last_comment_date": "2025-02-05T14:50:25+00:00"
  },
  {
    "id": 1660618100,
    "username": "unknow_acount",
    "first_name": "🇺🇦🇺🇦🇺🇦",
    "last_name": "🇺🇦🇺🇦🇺🇦",
    "premium": false,
    "phone": null,
    "last_seen": null,
    "comment_count": 1,
    "last_comment_date": "2025-02-05T14:48:51+00:00"
  },
  {
    "id": 452692480,
    "username": "dstackle",
    "first_name": "Do",
    "last_name": null,
    "premium": false,
    "phone": null,
    "last_seen": null,
    "comment_count": 1,
    "last_comment_date": "2025-02-05T14:47:24+00:00"
  },
  {
    "id": 7318999403,
    "username": null,
    "first_name": "Ххх",
    "last_name": "Ххх",
    "premium": false,
    "phone": null,
    "last_seen": null,
    "comment_count": 1,
    "last_comment_date": "2025-02-05T14:47:16+00:00"
  },
  {
    "id": 6928278738,
    "username": null,
    "first_name": "Александр",
    "last_name": null,
    "premium": false,
    "phone": null,
    "last_seen": null,
    "comment_count": 1,
    "last_comment_date": "2025-02-05T14:47:16+00:00"
  },
  {
    "id": 5298988778,
    "username": "onetwozero9x",
    "first_name": "Peter",
    "last_name": null,
    "premium": false,
    "phone": null,
    "last_seen": null,
    "comment_count": 1,
    "last_comment_date": "2025-02-05T14:45:22+00:00"
  },
  {
    "id": 259771981,
    "username": "Mr_Dufalak",
    "first_name": "Vladyslav",
    "last_name": null,
    "premium": false,
    "phone": null,
    "last_seen": null,
    "comment_count": 1,
    "last_comment_date": "2025-02-05T14:45:04+00:00"
  },
  {
    "id": 898454525,
    "username": "viktor_panasiuk97",
    "first_name": "Viktor",
    "last_name": null,
    "premium": false,
    "phone": null,
    "last_seen": null,
    "comment_count": 1,
    "last_comment_date": "2025-02-05T14:44:42+00:00"
  },
  {
    "id": 7025783170,
    "username": null,
    "first_name": "Кирилл",
    "last_name": null,
    "premium": false,
    "phone": null,
    "last_seen": null,
    "comment_count": 1,
    "last_comment_date": "2025-02-05T14:43:40+00:00"
  },
  {
    "id": 7816652793,
    "username": "max242530",
    "first_name": "Max",
    "last_name": null,
    "premium": false,
    "phone": null,
    "last_seen": null,
    "comment_count": 1,
    "last_comment_date": "2025-02-05T14:42:50+00:00"
  },
  {
    "id": 1234178662,
    "username": "AlaSka_Irl",
    "first_name": "AlaSka",
    "last_name": null,
    "premium": false,
    "phone": null,
    "last_seen": null,
    "comment_count": 1,
    "last_comment_date": "2025-02-05T14:42:18+00:00"
  },
  {
    "id": 7724647742,
    "username": null,
    "first_name": "Майк",
    "last_name": null,
    "premium": false,
    "phone": null,
    "last_seen": null,
    "comment_count": 2,
    "last_comment_date": "2025-02-05T14:40:48+00:00"
  },
  {
    "id": 238690868,
    "username": "le_cha",
    "first_name": "Лёша",
    "last_name": null,
    "premium": false,
    "phone": null,
    "last_seen": null,
    "comment_count": 2,
    "last_comment_date": "2025-02-05T14:38:09+00:00"
  },
  {
    "id": 7810039776,
    "username": "lucenzo1",
    "first_name": "Lucenzo",
    "last_name": null,
    "premium": false,
    "phone": null,
    "last_seen": null,
    "comment_count": 2,
    "last_comment_date": "2025-02-05T14:37:55+00:00"
  },
  {
    "id": 657028266,
    "username": "bessu4ka",
    "first_name": "Roman",
    "last_name": "Volkov",
    "premium": false,
    "phone": null,
    "last_seen": null,
    "comment_count": 1,
    "last_comment_date": "2025-02-05T14:37:32+00:00"
  },
  {
    "id": 6351886164,
    "username": null,
    "first_name": "Лысый",
    "last_name": null,
    "premium": false,
    "phone": null,
    "last_seen": null,
    "comment_count": 1,
    "last_comment_date": "2025-02-05T14:35:34+00:00"
  },
  {
    "id": 471706111,
    "username": "Andriy3079",
    "first_name": "Andriy",
    "last_name": "Kit",
    "premium": true,
    "phone": null,
    "last_seen": null,
    "comment_count": 1,
    "last_comment_date": "2025-02-05T14:35:26+00:00"
  }
]